fake_address_gen/__init__.py
fake_address_gen/create.py
fake_address_gen-0.0.2.dist-info/LICENSE
fake_address_gen-0.0.2.dist-info/METADATA
fake_address_gen-0.0.2.dist-info/WHEEL
fake_address_gen-0.0.2.dist-info/top_level.txt
fake_address_gen-0.0.2.dist-info/RECORD
