Metadata-Version: 2.1
Name: fake-address-gen
Version: 0.0.2
Summary: A small example package to generate fake user data
Home-page: https://github.com/Bishalsarang/fake-address-generator
Author: Bishal Sarangkoti
Author-email: sarangbishal@gmail.com
License: UNKNOWN
Platform: UNKNOWN
Classifier: Programming Language :: Python :: 3
Classifier: License :: OSI Approved :: MIT License
Classifier: Operating System :: OS Independent
Requires-Python: >=3.6
Requires-Dist: requests
Requires-Dist: bs4
